minegauler/__init__.py
minegauler/app/__init__.py
minegauler/app/__main__.py
minegauler/app/_version.py
minegauler/app/paths.py
minegauler/app/boards/sample.mgb
minegauler/app/core/__init__.py
minegauler/app/core/api.py
minegauler/app/core/board.py
minegauler/app/core/controller.py
minegauler/app/core/engine.py
minegauler/app/core/game.py
minegauler/app/core/minefield.py
minegauler/app/core/regular/__init__.py
minegauler/app/core/regular/board.py
minegauler/app/core/regular/controller.py
minegauler/app/core/regular/game.py
minegauler/app/core/regular/minefield.py
minegauler/app/core/regular/types.py
minegauler/app/core/split_cell/__init__.py
minegauler/app/core/split_cell/board.py
minegauler/app/core/split_cell/controller.py
minegauler/app/core/split_cell/game.py
minegauler/app/core/split_cell/minefield.py
minegauler/app/core/split_cell/types.py
minegauler/app/files/about.txt
minegauler/app/files/features.txt
minegauler/app/files/rules.txt
minegauler/app/files/tips.txt
minegauler/app/frontend/__init__.py
minegauler/app/frontend/highscores.py
minegauler/app/frontend/main_window.py
minegauler/app/frontend/panel.py
minegauler/app/frontend/state.py
minegauler/app/frontend/utils.py
minegauler/app/frontend/minefield/__init__.py
minegauler/app/frontend/minefield/_base.py
minegauler/app/frontend/minefield/regular.py
minegauler/app/frontend/minefield/simulate.py
minegauler/app/frontend/minefield/split_cell.py
minegauler/app/highscores/__init__.py
minegauler/app/highscores/base.py
minegauler/app/highscores/mysql.py
minegauler/app/highscores/sqlite.py
minegauler/app/highscores/compat/__init__.py
minegauler/app/highscores/compat/sqlite_v0.py
minegauler/app/highscores/compat/sqlite_v1.py
minegauler/app/highscores/compat/sqlite_v2.py
minegauler/app/images/icon.ico
minegauler/app/images/buttons/Butterfly/btn_down.png
minegauler/app/images/buttons/Butterfly/btn_down_hit.png
minegauler/app/images/buttons/Butterfly/btn_down_life.png
minegauler/app/images/buttons/Butterfly/btn_up.png
minegauler-4.2.0.dist-info/LICENSE.txt
minegauler-4.2.0.dist-info/METADATA
minegauler-4.2.0.dist-info/WHEEL
minegauler-4.2.0.dist-info/entry_points.txt
minegauler-4.2.0.dist-info/top_level.txt
minegauler-4.2.0.dist-info/RECORD
