Metadata-Version: 2.2
Name: minegauler
Version: 4.2.0
Summary: A clone of the original minesweeper game with many added features
Author-email: Lewis Gaul <minegauler@gmail.com>
Project-URL: Bug Reports, https://github.com/LewisGaul/minegauler/issues
Project-URL: Source, https://github.com/LewisGaul/minegauler/
Project-URL: Background, https://www.lewisgaul.co.uk/blog/coding/2020/02/12/minegauler/
Keywords: minesweeper,game,puzzle
Classifier: Programming Language :: Python :: 3
Classifier: License :: OSI Approved :: GNU General Public License v3 (GPLv3)
Classifier: Operating System :: OS Independent
Classifier: Development Status :: 5 - Production/Stable
Classifier: Intended Audience :: End Users/Desktop
Classifier: Natural Language :: English
Classifier: Topic :: Games/Entertainment :: Puzzle Games
Requires-Python: >=3.9
License-File: LICENSE.txt
Requires-Dist: attrs
Requires-Dist: PyQt6
Requires-Dist: requests
Requires-Dist: pytz
Requires-Dist: tabulate
Requires-Dist: typing-extensions
Requires-Dist: zig-minesolver<0.2,>=0.1.1
